<?xml version="1.0" encoding="UTF-8"?>
<metadata id="020-MPP1285_22-TITLEPAGE">
	<file family="145" manual="AMM" pn="1285" chg="U" tsn="51" is_tr="false">
		<title>AMM PART II-1285 - AUTO FLIGHT</title>
		<path>/CHAPTER_22</path>
		<hash>0c2145fe0471be651d9150e3efa4fda2</hash>
	</file>
	<pages>
		<page number="1" width="216.0" height="279.0">
			<data>AIRCRAFT MAINTENANCE MANUAL CHAPTER 22 AUTO FLIGHT Copyright Â© by Embraer S.A. All rights reserved - See title page for details.</data>
		</page>
		<page number="2" width="216.0" height="279.0">
			<data/>
		</page>
	</pages>
</metadata>
